<?xml version="1.0"?>
<CopyObject xmlns:xsi="http://www.w3.org/2001/XMLSchema-instance" xmlns:xsd="http://www.w3.org/2001/XMLSchema">
  <Name>Sql Server Sample 1</Name>
  <Dbms>Sql Server</Dbms>
  <Source>Data Source=.\sqlexpress;Initial Catalog=c3o.shared.0.0.0.1.fnoodle;Integrated Security=True</Source>
  <Destination>Data Source=.\sqlexpress;Initial Catalog=c3o.shared.0.0.0.1.sqlcopy;Integrated Security=True</Destination>
  <BatchSize>0</BatchSize>
  <BulkCopyOptions>0</BulkCopyOptions>
  <BulkCopyTimeout>30</BulkCopyTimeout>
  <NotifyAfter>0</NotifyAfter>
  <Default>false</Default>
  <UseInternalTransaction>false</UseInternalTransaction>
  <DestinationPartitionName />
  <CheckConstraints>true</CheckConstraints>
  <FireTriggers>true</FireTriggers>
  <KeepIdentity>true</KeepIdentity>
  <KeepNulls>true</KeepNulls>
  <TableLock>false</TableLock>
  <DeleteRows>true</DeleteRows>
  <PreCopySql>exec sp_msforeachtable 'ALTER TABLE ? NOCHECK CONSTRAINT all'; exec sp_msforeachtable 'ALTER TABLE ? DISABLE TRIGGER all'; </PreCopySql>
  <PostCopySql>exec sp_msforeachtable 'ALTER TABLE ? CHECK CONSTRAINT all'; exec sp_msforeachtable 'ALTER TABLE ? ENABLE TRIGGER all'; </PostCopySql>
  <ListSql>SELECT '[' + table_schema + '].[' + table_name + ']' as table_name FROM information_schema.tables</ListSql>
  <DeleteSql>delete from {0}</DeleteSql>
  <SelectSql>select * from {0}</SelectSql>
  <Tables>
    <TableObject>
      <Name>[dbo].[shared_PageClass]</Name>
      <Selected>false</Selected>
      <Status />
    </TableObject>
    <TableObject>
      <Name>[dbo].[shared_Site]</Name>
      <Selected>false</Selected>
      <Status />
    </TableObject>
    <TableObject>
      <Name>[dbo].[shared_Server]</Name>
      <Selected>false</Selected>
      <Status />
    </TableObject>
    <TableObject>
      <Name>[dbo].[shared_Role]</Name>
      <Selected>false</Selected>
      <Status />
    </TableObject>
    <TableObject>
      <Name>[dbo].[shared_Address]</Name>
      <Selected>false</Selected>
      <Status />
    </TableObject>
    <TableObject>
      <Name>[dbo].[shared_Person]</Name>
      <Selected>false</Selected>
      <Status />
    </TableObject>
    <TableObject>
      <Name>[dbo].[old_shared_LookupCategory]</Name>
      <Selected>false</Selected>
      <Status />
    </TableObject>
    <TableObject>
      <Name>[dbo].[shared_SessionArchive]</Name>
      <Selected>false</Selected>
      <Status />
    </TableObject>
    <TableObject>
      <Name>[dbo].[shared_Tag]</Name>
      <Selected>false</Selected>
      <Status />
    </TableObject>
    <TableObject>
      <Name>[dbo].[shared_Component]</Name>
      <Selected>false</Selected>
      <Status />
    </TableObject>
    <TableObject>
      <Name>[dbo].[shared_Page]</Name>
      <Selected>false</Selected>
      <Status />
    </TableObject>
    <TableObject>
      <Name>[dbo].[shared_PageRoute]</Name>
      <Selected>false</Selected>
      <Status />
    </TableObject>
    <TableObject>
      <Name>[dbo].[shared_SiteComponent]</Name>
      <Selected>false</Selected>
      <Status />
    </TableObject>
    <TableObject>
      <Name>[dbo].[shared_Session]</Name>
      <Selected>false</Selected>
      <Status />
    </TableObject>
    <TableObject>
      <Name>[dbo].[shared_PersonSiteAccess]</Name>
      <Selected>false</Selected>
      <Status />
    </TableObject>
    <TableObject>
      <Name>[dbo].[shared_SessionMessage]</Name>
      <Selected>false</Selected>
      <Status />
    </TableObject>
    <TableObject>
      <Name>[dbo].[shared_PersonAccountAccess]</Name>
      <Selected>false</Selected>
      <Status />
    </TableObject>
    <TableObject>
      <Name>[dbo].[shared_PageDetailSecurity]</Name>
      <Selected>false</Selected>
      <Status />
    </TableObject>
    <TableObject>
      <Name>[dbo].[shared_ComponentSecurity]</Name>
      <Selected>false</Selected>
      <Status />
    </TableObject>
    <TableObject>
      <Name>[dbo].[shared_ContentSecurity]</Name>
      <Selected>false</Selected>
      <Status />
    </TableObject>
    <TableObject>
      <Name>[dbo].[Shared_DataType]</Name>
      <Selected>false</Selected>
      <Status />
    </TableObject>
    <TableObject>
      <Name>[dbo].[shared_SessionSiteAccess]</Name>
      <Selected>false</Selected>
      <Status />
    </TableObject>
    <TableObject>
      <Name>[dbo].[shared_DataValue]</Name>
      <Selected>false</Selected>
      <Status />
    </TableObject>
    <TableObject>
      <Name>[dbo].[shared_PageSecurity]</Name>
      <Selected>false</Selected>
      <Status />
    </TableObject>
    <TableObject>
      <Name>[dbo].[shared_PersonAddress]</Name>
      <Selected>false</Selected>
      <Status />
    </TableObject>
    <TableObject>
      <Name>[dbo].[shared_AccountData]</Name>
      <Selected>false</Selected>
      <Status />
    </TableObject>
    <TableObject>
      <Name>[dbo].[shared_PersonData]</Name>
      <Selected>false</Selected>
      <Status />
    </TableObject>
    <TableObject>
      <Name>[dbo].[shared_Account]</Name>
      <Selected>false</Selected>
      <Status />
    </TableObject>
    <TableObject>
      <Name>[dbo].[shared_PersonPageDetail]</Name>
      <Selected>false</Selected>
      <Status />
    </TableObject>
    <TableObject>
      <Name>[dbo].[shared_AccountUpload]</Name>
      <Selected>false</Selected>
      <Status />
    </TableObject>
    <TableObject>
      <Name>[dbo].[old_shared_LookupValue]</Name>
      <Selected>false</Selected>
      <Status />
    </TableObject>
    <TableObject>
      <Name>[dbo].[shared_ContentTag]</Name>
      <Selected>false</Selected>
      <Status />
    </TableObject>
    <TableObject>
      <Name>[dbo].[shared_AccountTag]</Name>
      <Selected>false</Selected>
      <Status />
    </TableObject>
    <TableObject>
      <Name>[dbo].[shared_SessionPageDetail]</Name>
      <Selected>false</Selected>
      <Status />
    </TableObject>
    <TableObject>
      <Name>[dbo].[shared_AccountSecurity]</Name>
      <Selected>false</Selected>
      <Status />
    </TableObject>
    <TableObject>
      <Name>[dbo].[shared_PageDetail]</Name>
      <Selected>false</Selected>
      <Status />
    </TableObject>
    <TableObject>
      <Name>[dbo].[shared_SessionData]</Name>
      <Selected>false</Selected>
      <Status />
    </TableObject>
    <TableObject>
      <Name>[dbo].[shared_SessionViewstate]</Name>
      <Selected>false</Selected>
      <Status />
    </TableObject>
    <TableObject>
      <Name>[dbo].[shared_AccountContent]</Name>
      <Selected>false</Selected>
      <Status />
    </TableObject>
    <TableObject>
      <Name>[dbo].[sysdiagrams]</Name>
      <Selected>false</Selected>
      <Status />
    </TableObject>
    <TableObject>
      <Name>[dbo].[shared_PageCount]</Name>
      <Selected>false</Selected>
      <Status />
    </TableObject>
  </Tables>
</CopyObject>
